ir_support/__init__.py
ir_support/classes/DHRobotPlotter.py
ir_support/classes/EllipsoidRobot.py
ir_support/classes/RectangularPrism.py
ir_support/classes/__init__.py
ir_support/functions/__init__.py
ir_support/functions/clean_SE2.py
ir_support/functions/draw_possible_ellipse_given_foci.py
ir_support/functions/line_plane_intersection.py
ir_support/functions/make_ellipsoid.py
ir_support/functions/orthogonalize_rotation.py
ir_support/functions/swift_plotting.py
ir_support/functions/tranimate_custom.py
ir_support/plyclasses/Haneubu+uf.ply
ir_support/plyclasses/RobotCow.py
ir_support/plyclasses/SwiftUFOFleet.py
ir_support/plyclasses/UFOFleet.py
ir_support/plyclasses/__init__.py
ir_support/plyclasses/cow.ply
ir_support/plyclasses/fenceFinal.ply
ir_support/plyclasses/hit_ufo.dae
ir_support/plyclasses/pen.dae
ir_support/plyclasses/ufo.dae
ir_support/plyprocess/__init__.py
ir_support/plyprocess/ply_processing.py
ir_support/robots/DHRobot3D.py
ir_support/robots/DensoVS060/DensoVS060.py
ir_support/robots/DensoVS060/DensoVS060.urdf
ir_support/robots/DensoVS060/DensoVS060_demo.py
ir_support/robots/DensoVS060/__init__.py
ir_support/robots/DensoVS060/meshes/DensoVS060.blend
ir_support/robots/DensoVS060/meshes/DensoVS060Link0.dae
ir_support/robots/DensoVS060/meshes/DensoVS060Link1.dae
ir_support/robots/DensoVS060/meshes/DensoVS060Link2.dae
ir_support/robots/DensoVS060/meshes/DensoVS060Link3.dae
ir_support/robots/DensoVS060/meshes/DensoVS060Link4.dae
ir_support/robots/DensoVS060/meshes/DensoVS060Link5.dae
ir_support/robots/DensoVS060/meshes/DensoVS060Link6.dae
ir_support/robots/DensoVS060/meshes/DensoVS060_ply_files_and_model_from_MATLAB.7z
ir_support/robots/LinearUR3/LinearUR3.py
ir_support/robots/LinearUR3/LinearUR3_v2.blend
ir_support/robots/LinearUR3/__init__.py
ir_support/robots/LinearUR3/base_rail.stl
ir_support/robots/LinearUR3/forearm_ur3.dae
ir_support/robots/LinearUR3/shoulder_ur3.dae
ir_support/robots/LinearUR3/slider_rail.stl
ir_support-1.2.6.dist-info/LICENSE.md
ir_support-1.2.6.dist-info/METADATA
ir_support-1.2.6.dist-info/WHEEL
ir_support-1.2.6.dist-info/RECORD
